.gitattributes
.gitignore
.gitmodules
LICENSE
MANIFEST.in
README.rst
setup.cfg
setup.py
tox.ini
Mopidy_jukePi.egg-info/PKG-INFO
Mopidy_jukePi.egg-info/SOURCES.txt
Mopidy_jukePi.egg-info/dependency_links.txt
Mopidy_jukePi.egg-info/entry_points.txt
Mopidy_jukePi.egg-info/not-zip-safe
Mopidy_jukePi.egg-info/requires.txt
Mopidy_jukePi.egg-info/top_level.txt
mopidy_jukepi/__init__.py
mopidy_jukepi/__init__.pyc
mopidy_jukepi/ext.conf
mopidy_jukepi/static/favicon.ico
mopidy_jukepi/static/css/app.css
mopidy_jukepi/static/fonts/MaterialIcons-Regular.eot
mopidy_jukepi/static/fonts/MaterialIcons-Regular.svg
mopidy_jukepi/static/fonts/MaterialIcons-Regular.ttf
mopidy_jukepi/static/fonts/MaterialIcons-Regular.woff
mopidy_jukepi/static/fonts/MaterialIcons-Regular.woff2
mopidy_jukepi/static/img/landing_logo.png
mopidy_jukepi/static/img/loading.gif
mopidy_jukepi/static/js/app.js
mopidy_jukepi/static/js/bundle.js
mopidy_jukepi/templates/index.html
tests/__init__.py
tests/test_extension.py