Metadata-Version: 1.1
Name: Mopidy-jukePi
Version: 1.0.6
Summary: Mopidy web client extension
Home-page: https://github.com/connrs/mopidy-jukepi
Author: connrs
Author-email: paul.connolley@gmail.com
License: Apache License, Version 2.0
Platform: UNKNOWN
Classifier: Environment :: No Input/Output (Daemon)
Classifier: Intended Audience :: End Users/Desktop
Classifier: License :: OSI Approved :: Apache Software License
Classifier: Operating System :: OS Independent
Classifier: Programming Language :: Python :: 2
Classifier: Topic :: Multimedia :: Sound/Audio :: Players
